MANIFEST.in
README.md
pyproject.toml
setup.py
amuse_mobse.egg-info/PKG-INFO
amuse_mobse.egg-info/SOURCES.txt
amuse_mobse.egg-info/dependency_links.txt
amuse_mobse.egg-info/requires.txt
amuse_mobse.egg-info/top_level.txt
src/amuse/community/mobse/Makefile
src/amuse/community/mobse/__init__.py
src/amuse/community/mobse/_version.py
src/amuse/community/mobse/interface.f
src/amuse/community/mobse/interface.py
src/amuse/community/mobse/src/Makefile
src/amuse/community/mobse/src/README_MOBSE
src/amuse/community/mobse/src/binary.in
src/amuse/community/mobse/src/comenv.f
src/amuse/community/mobse/src/const_mobse.h
src/amuse/community/mobse/src/corerd.f
src/amuse/community/mobse/src/deltat.f
src/amuse/community/mobse/src/dgcore.f
src/amuse/community/mobse/src/eddington.f
src/amuse/community/mobse/src/evolv3.f
src/amuse/community/mobse/src/fallback.f
src/amuse/community/mobse/src/gntage.f
src/amuse/community/mobse/src/hrdiag.f
src/amuse/community/mobse/src/instar.f
src/amuse/community/mobse/src/kick.f
src/amuse/community/mobse/src/mix.f
src/amuse/community/mobse/src/mlwind.f
src/amuse/community/mobse/src/mobse.f
src/amuse/community/mobse/src/mrenv.f
src/amuse/community/mobse/src/pisn.f
src/amuse/community/mobse/src/ran3.f
src/amuse/community/mobse/src/rl.f
src/amuse/community/mobse/src/star.f
src/amuse/community/mobse/src/zcnsts.f
src/amuse/community/mobse/src/zdata.h
src/amuse/community/mobse/src/zfuncs.f
support/__init__.py
support/classifiers.py
support/config.py
support/generate_main.py
support/getsp.class
support/getsp.java
support/misc.py
support/setup_codes.py
support/version.py